jupyterlab_prolog_codemirror_extension/__init__.py
jupyterlab_prolog_codemirror_extension/_version.py
jupyterlab_prolog_codemirror_extension/labextension/build_log.json
jupyterlab_prolog_codemirror_extension/labextension/package.json
jupyterlab_prolog_codemirror_extension/labextension/static/lib_index_js.9edcdbe5c5a75e025f3b.js
jupyterlab_prolog_codemirror_extension/labextension/static/lib_index_js.9edcdbe5c5a75e025f3b.js.map
jupyterlab_prolog_codemirror_extension/labextension/static/remoteEntry.526702c07bb0a9d48e63.js
jupyterlab_prolog_codemirror_extension/labextension/static/remoteEntry.526702c07bb0a9d48e63.js.map
jupyterlab_prolog_codemirror_extension/labextension/static/style.js
jupyterlab_prolog_codemirror_extension/labextension/static/style_index_js.40a6d40708158507be5e.js
jupyterlab_prolog_codemirror_extension/labextension/static/style_index_js.40a6d40708158507be5e.js.map
jupyterlab_prolog_codemirror_extension/labextension/static/vendors-node_modules_css-loader_dist_runtime_api_js-node_modules_css-loader_dist_runtime_cssW-72eba1.efd6585dc97055e732c4.js
jupyterlab_prolog_codemirror_extension/labextension/static/vendors-node_modules_css-loader_dist_runtime_api_js-node_modules_css-loader_dist_runtime_cssW-72eba1.efd6585dc97055e732c4.js.map
jupyterlab_prolog_codemirror_extension-0.0.2.data/data/share/jupyter/labextensions/jupyterlab_prolog_codemirror_extension/build_log.json
jupyterlab_prolog_codemirror_extension-0.0.2.data/data/share/jupyter/labextensions/jupyterlab_prolog_codemirror_extension/install.json
jupyterlab_prolog_codemirror_extension-0.0.2.data/data/share/jupyter/labextensions/jupyterlab_prolog_codemirror_extension/package.json
jupyterlab_prolog_codemirror_extension-0.0.2.data/data/share/jupyter/labextensions/jupyterlab_prolog_codemirror_extension/static/lib_index_js.9edcdbe5c5a75e025f3b.js
jupyterlab_prolog_codemirror_extension-0.0.2.dist-info/LICENSE
jupyterlab_prolog_codemirror_extension-0.0.2.dist-info/METADATA
jupyterlab_prolog_codemirror_extension-0.0.2.dist-info/WHEEL
jupyterlab_prolog_codemirror_extension-0.0.2.dist-info/top_level.txt
jupyterlab_prolog_codemirror_extension-0.0.2.dist-info/RECORD
